Metadata-Version: 1.1
Name: snackwich
Version: 1.1
Summary: Configuration-based console UI forms.
Home-page: https://github.com/dsoprea/Snackwich
Author: Dustin Oprea
Author-email: myselfasunder@gmail.com
License: New BSD
Keywords: console ui newt snack forms
Platform: UNKNOWN
Classifier: Topic :: Software Development :: Libraries :: Python Modules
Classifier: Environment :: Console :: Newt
